schema2type/__init__.py
schema2type/__main__.py
schema2type/commands/__init__.py
schema2type/commands/gen_stubs.py
schema2type-0.0.3.dist-info/LICENSE
schema2type-0.0.3.dist-info/METADATA
schema2type-0.0.3.dist-info/WHEEL
schema2type-0.0.3.dist-info/entry_points.txt
schema2type-0.0.3.dist-info/top_level.txt
schema2type-0.0.3.dist-info/RECORD
