Metadata-Version: 2.1
Name: schema2type
Version: 0.0.3
Summary: Interact with JSON or YAML content as if it's a Python object
Home-page: https://github.com/mokkit/schema2type
Author: Steyn Huurman
Author-email: steyn@mokkit.eu
License: Apache 2.0
Platform: UNKNOWN
Classifier: Programming Language :: Python :: 3
Classifier: License :: OSI Approved :: Apache Software License
Classifier: Operating System :: OS Independent
Requires-Python: >=3.6
Requires-Dist: prance (==0.20.2)
Requires-Dist: openapi-schema-validator (==0.1.5)
Requires-Dist: click (==7.1.2)
Requires-Dist: PyYAML (==5.4.1)
Requires-Dist: openapi-spec-validator (==0.3.0)
